MANIFEST.in
README.rst
VERSION.txt
known-test-failures.json
pyproject.toml
pyproject.toml.m4
requirements-editable.txt.m4
requirements.txt.m4
setup.py
tox.ini
bin/math-readline
bin/sage
bin/sage-cachegrind
bin/sage-callgrind
bin/sage-cleaner
bin/sage-coverage
bin/sage-env
bin/sage-env-config.in
bin/sage-eval
bin/sage-fixdoctests
bin/sage-grep
bin/sage-grepdoc
bin/sage-inline-fortran
bin/sage-ipynb2rst
bin/sage-ipython
bin/sage-list-packages
bin/sage-massif
bin/sage-notebook
bin/sage-num-threads.py
bin/sage-omega
bin/sage-preparse
bin/sage-python
bin/sage-run
bin/sage-run-cython
bin/sage-runtests
bin/sage-src-env-config.in
bin/sage-startuptime.py
bin/sage-valgrind
bin/sage-venv-config
bin/sage-version.sh
sage/all__sagemath_repl.py
sage/doctest/__init__.py
sage/doctest/__main__.py
sage/doctest/all.py
sage/doctest/check_tolerance.py
sage/doctest/control.py
sage/doctest/external.py
sage/doctest/fixtures.py
sage/doctest/forker.py
sage/doctest/marked_output.py
sage/doctest/parsing.py
sage/doctest/parsing_test.py
sage/doctest/reporting.py
sage/doctest/rif_tol.py
sage/doctest/sources.py
sage/doctest/test.py
sage/doctest/util.py
sage/doctest/tests/1second.rst
sage/doctest/tests/99seconds.rst
sage/doctest/tests/abort.rst
sage/doctest/tests/atexit.rst
sage/doctest/tests/fail_and_die.rst
sage/doctest/tests/initial.rst
sage/doctest/tests/interrupt.rst
sage/doctest/tests/interrupt_diehard.rst
sage/doctest/tests/keyboardinterrupt.rst
sage/doctest/tests/longtime.rst
sage/doctest/tests/nodoctest
sage/doctest/tests/random_seed.rst
sage/doctest/tests/show_skipped.rst
sage/doctest/tests/sig_on.rst
sage/doctest/tests/simple_failure.rst
sage/doctest/tests/sleep2.rst
sage/doctest/tests/sleep_and_raise.rst
sage/doctest/tests/tolerance.rst
sage/interfaces/quit.py
sage/misc/all__sagemath_repl.py
sage/misc/banner.py
sage/misc/sage_eval.py
sage/misc/sage_input.py
sage/misc/sagedoc.py
sage/repl/__init__.py
sage/repl/all.py
sage/repl/attach.py
sage/repl/configuration.py
sage/repl/image.py
sagemath_repl.egg-info/PKG-INFO
sagemath_repl.egg-info/SOURCES.txt
sagemath_repl.egg-info/dependency_links.txt
sagemath_repl.egg-info/requires.txt
sagemath_repl.egg-info/top_level.txt