Metadata-Version: 2.1
Name: sagemath-repl
Version: 10.7b9
Summary: Sage: Open Source Mathematics Software: IPython kernel, Sage preparser, doctester
Author-email: The Sage Developers <sage-support@googlegroups.com>
License: GNU General Public License (GPL) v2 or later
Project-URL: download, https://doc.sagemath.org/html/en/installation/index.html
Project-URL: release notes, https://github.com/sagemath/sage/releases
Project-URL: source, https://github.com/sagemath/sage
Project-URL: documentation, https://doc.sagemath.org
Project-URL: homepage, https://www.sagemath.org
Project-URL: tracker, https://github.com/sagemath/sage/issues
Classifier: Development Status :: 6 - Mature
Classifier: Intended Audience :: Education
Classifier: Intended Audience :: Science/Research
Classifier: License :: OSI Approved :: GNU General Public License v2 or later (GPLv2+)
Classifier: Operating System :: POSIX
Classifier: Operating System :: MacOS :: MacOS X
Classifier: Programming Language :: Python :: 3 :: Only
Classifier: Programming Language :: Python :: 3.9
Classifier: Programming Language :: Python :: 3.10
Classifier: Programming Language :: Python :: 3.11
Classifier: Programming Language :: Python :: 3.12
Classifier: Programming Language :: Python :: Implementation :: CPython
Classifier: Topic :: Scientific/Engineering :: Mathematics
Requires-Python: <3.13,>=3.9
Requires-Dist: sagemath-objects~=10.7b9
Requires-Dist: sagemath-environment~=10.7b9
Requires-Dist: ipykernel>=5.2.1
Requires-Dist: ipython>=7.13.0
Requires-Dist: ipywidgets>=7.5.1
Requires-Dist: jupyter-client
Provides-Extra: sphinx
Requires-Dist: sphinx<9,>=7.4.7; extra == "sphinx"
